pyfinlab/__init__.py
pyfinlab/backtesting.py
pyfinlab/charts.py
pyfinlab/cov_matrix_test.py
pyfinlab/data_api.py
pyfinlab/performance.py
pyfinlab/portfolio_optimization.py
pyfinlab/report_generation.py
pyfinlab/return_models.py
pyfinlab/risk_models.py
pyfinlab/stock_to_flow.py
pyfinlab/variance_inflation_factor.py
pyfinlab-0.0.30.dist-info/LICENSE.txt
pyfinlab-0.0.30.dist-info/METADATA
pyfinlab-0.0.30.dist-info/WHEEL
pyfinlab-0.0.30.dist-info/top_level.txt
pyfinlab-0.0.30.dist-info/RECORD
