Metadata-Version: 2.1
Name: pyfinlab
Version: 0.0.30
Summary: Financial applications for portfolio management
Home-page: https://github.com/nathanramoscfa/pyfinlab
Author: Nathan Ramos, CFA©
Author-email: nathan.ramos.cfa@gmail.com
License: UNKNOWN
Project-URL: Bug Reports, https://github.com/nathanramoscfa/pyfinlab/issues
Project-URL: Source, https://github.com/nathanramoscfa/pyfinlab
Keywords: python,finance,portfolio-optimization,quantitative-finance,portfolio-management
Platform: UNKNOWN
Classifier: Development Status :: 3 - Alpha
Classifier: Intended Audience :: Developers
Classifier: Intended Audience :: Education
Classifier: Intended Audience :: Financial and Insurance Industry
Classifier: Intended Audience :: Science/Research
Classifier: Topic :: Office/Business :: Financial :: Investment
Classifier: Topic :: Software Development :: Libraries :: Python Modules
Classifier: License :: OSI Approved :: BSD License
Classifier: Programming Language :: Python :: 3
Requires-Python: >=3.7
License-File: LICENSE.txt
